[
    {
        "Judul": "Pengumuman Putusan Penundaan Kewajiban Pembayaran Utang PT Maleo",
        "Kategori": "Native",
        "Waktu Publish": "10 jam yang lalu",
        "Waktu Scrapping": "05 April 2024 17:21:00"
    },
    {
        "Judul": "KSAU: Presiden ingin AU Tumbuh Lebih Kuat Jaga Kedaulatan Negara",
        "Kategori": "News",
        "Waktu Publish": "59 detik yang lalu",
        "Waktu Scrapping": "05 April 2024 17:21:00"
    },
    {
        "Judul": "Presiden Melantik Mohamad Tonny Harjono menjadi KSAU",
        "Kategori": "Visual",
        "Waktu Publish": "3 menit yang lalu",
        "Waktu Scrapping": "05 April 2024 17:21:00"
    },
    {
        "Judul": "Tujuh Waralaba Film Fantasi Ini Jadi Favorit Penggemar, Anda Juga Suka?",
        "Kategori": "Ameera",
        "Waktu Publish": "5 menit yang lalu",
        "Waktu Scrapping": "05 April 2024 17:21:00"
    },
    {
        "Judul": "PTPN IV PalmCo Berangkatkan 500 Pemudik Secara Gratis ke Tujuh Kota di Sumatra",
        "Kategori": "Ekonomi",
        "Waktu Publish": "6 menit yang lalu",
        "Waktu Scrapping": "05 April 2024 17:21:00"
    },
    {
        "Judul": "Wabah Flu Burung Tidak Menimbulkan Risiko Terhadap Keamanan Pasokan Makanan Amerika, Ini kata Para A",
        "Kategori": "Network",
        "Waktu Publish": "7 menit yang lalu",
        "Waktu Scrapping": "05 April 2024 17:21:00"
    },
    {
        "Judul": "LPEI Dorong 104 Pelaku UKM Perluas Pasar Ekspor di Awal 2024",
        "Kategori": "Network",
        "Waktu Publish": "7 menit yang lalu",
        "Waktu Scrapping": "05 April 2024 17:21:00"
    },
    {
        "Judul": "Terungkap Arahan Presiden Jokowi Sebelum Airlangga Hadiri Sidang MK",
        "Kategori": "Pemilu Kita",
        "Waktu Publish": "14 menit yang lalu",
        "Waktu Scrapping": "05 April 2024 17:21:00"
    },
    {
        "Judul": "Gibran Minta Tempat Makan di Solo Pasang Harga Normal Selama Libur Lebaran",
        "Kategori": "Ramadhan",
        "Waktu Publish": "15 menit yang lalu",
        "Waktu Scrapping": "05 April 2024 17:21:00"
    },
    {
        "Judul": "H-5 Lebaran, 25.603 Pemudik Berangkat dari Stasiun di Daop 8 Surabaya",
        "Kategori": "Ramadhan",
        "Waktu Publish": "15 menit yang lalu",
        "Waktu Scrapping": "05 April 2024 17:21:00"
    },
    {
        "Judul": "Astra Infra Imbau Pemudik Rencanakan Perjalanan dengan Baik",
        "Kategori": "Ramadhan",
        "Waktu Publish": "16 menit yang lalu",
        "Waktu Scrapping": "05 April 2024 17:21:00"
    },
    {
        "Judul": "Transjakarta Rute 10M Akan Diuji Coba Usai Lebaran",
        "Kategori": "News",
        "Waktu Publish": "16 menit yang lalu",
        "Waktu Scrapping": "05 April 2024 17:21:00"
    },
    {
        "Judul": "RUU DKJ Jadi UU, Fahira Idris: Kawasan Aglomerasi akan Jadi Tantangan Besar",
        "Kategori": "Network",
        "Waktu Publish": "19 menit yang lalu",
        "Waktu Scrapping": "05 April 2024 17:21:00"
    },
    {
        "Judul": "Isu Rencana Pembubaran KPK dengan Cara Dilebur dengan Ombudsman",
        "Kategori": "News",
        "Waktu Publish": "19 menit yang lalu",
        "Waktu Scrapping": "05 April 2024 17:21:00"
    },
    {
        "Judul": "24 Mualaf Berikrar Syahadat di Masjid Al Akbar Surabaya Sepanjang Ramadhan",
        "Kategori": "Khazanah",
        "Waktu Publish": "20 menit yang lalu",
        "Waktu Scrapping": "05 April 2024 17:21:00"
    },
    {
        "Judul": "Posko Kebencanaan Disiagakan pada Lebaran",
        "Kategori": "Ramadhan",
        "Waktu Publish": "21 menit yang lalu",
        "Waktu Scrapping": "05 April 2024 17:21:00"
    },
    {
        "Judul": "Petugas Gabungan di Sukabumi Awasi Keamanan Pangan Jelang Lebaran",
        "Kategori": "Network",
        "Waktu Publish": "22 menit yang lalu",
        "Waktu Scrapping": "05 April 2024 17:21:00"
    },
    {
        "Judul": "Lalu Lintas Bus Arus Mudik di Terminal Jombor Sleman Meningkat",
        "Kategori": "Rejogja",
        "Waktu Publish": "23 menit yang lalu",
        "Waktu Scrapping": "05 April 2024 17:21:00"
    },
    {
        "Judul": "Terungkap Alasan Mensos Risma Jarang Turun Gunung Bagikan Bansos",
        "Kategori": "Pemilu Kita",
        "Waktu Publish": "24 menit yang lalu",
        "Waktu Scrapping": "05 April 2024 17:21:00"
    },
    {
        "Judul": "Pantura Siang Suhu Panas, Malam Hujan, Pemudik Diminta Waspadai Cuaca Ekstrim",
        "Kategori": "Network",
        "Waktu Publish": "29 menit yang lalu",
        "Waktu Scrapping": "05 April 2024 17:21:00"
    },
    {
        "Judul": "Jasa Marga: 322 Ribu Kendaraan ke Luar Jabotabek Hingga H-6 Lebaran",
        "Kategori": "Ramadhan",
        "Waktu Publish": "30 menit yang lalu",
        "Waktu Scrapping": "05 April 2024 17:21:00"
    },
    {
        "Judul": "Dua Terduga Anggota KKB Ditembak Mati Karena Tembaki Pendulang Emas",
        "Kategori": "News",
        "Waktu Publish": "31 menit yang lalu",
        "Waktu Scrapping": "05 April 2024 17:21:00"
    },
    {
        "Judul": "Airlangga Pasang Badan Soal Jokowi Sering Kunjungi Jawa Tengah",
        "Kategori": "Pemilu Kita",
        "Waktu Publish": "36 menit yang lalu",
        "Waktu Scrapping": "05 April 2024 17:21:00"
    },
    {
        "Judul": "Mudik Gratis Mudahkan Warga Perantauan Kembali ke Kampung Halaman",
        "Kategori": "Ramadhan",
        "Waktu Publish": "36 menit yang lalu",
        "Waktu Scrapping": "05 April 2024 17:21:00"
    },
    {
        "Judul": "Pemabuk Tabrak Ojol Hingga Tewas, Ini Alasan Minum Khamr Jadi Pintu Semua Kejahatan",
        "Kategori": "Ameera",
        "Waktu Publish": "38 menit yang lalu",
        "Waktu Scrapping": "05 April 2024 17:21:00"
    },
    {
        "Judul": "Bayi dalam Kandungan, Apakah Wajib Bayar Zakat Fitrah?",
        "Kategori": "Ramadhan",
        "Waktu Publish": "38 menit yang lalu",
        "Waktu Scrapping": "05 April 2024 17:21:00"
    },
    {
        "Judul": "Ini Pesan Jokowi Usai Melantik KSAU Marsekal Tonny Harjono",
        "Kategori": "News",
        "Waktu Publish": "41 menit yang lalu",
        "Waktu Scrapping": "05 April 2024 17:21:00"
    },
    {
        "Judul": "Erick Thohir Sediakan Bus Mudik Khusus Bagi Difabel",
        "Kategori": "Ekonomi",
        "Waktu Publish": "42 menit yang lalu",
        "Waktu Scrapping": "05 April 2024 17:21:00"
    },
    {
        "Judul": "Polisi Jemput Paksa Korban Penembakan Gathan Saleh",
        "Kategori": "News",
        "Waktu Publish": "45 menit yang lalu",
        "Waktu Scrapping": "05 April 2024 17:21:00"
    },
    {
        "Judul": "Sejak 1988, Padmarajan Caleg Asal India Gagal Terus Masuk Parlemen",
        "Kategori": "Video",
        "Waktu Publish": "47 menit yang lalu",
        "Waktu Scrapping": "05 April 2024 17:21:00"
    },
    {
        "Judul": "Liburan Aman dan Asik Bersama Digiask by Askrindo",
        "Kategori": "Network",
        "Waktu Publish": "50 menit yang lalu",
        "Waktu Scrapping": "05 April 2024 17:21:00"
    },
    {
        "Judul": "Perubahan Iklim Mempengaruhi Rotasi Bumi dan Waktu",
        "Kategori": "Tekno",
        "Waktu Publish": "51 menit yang lalu",
        "Waktu Scrapping": "05 April 2024 17:21:00"
    },
    {
        "Judul": "Ajang Sepak Bola Bergengsi Kembali Undang Klub Indonesia dan Negara ASEAN Lewat Shopee Cup",
        "Kategori": "Sport",
        "Waktu Publish": "51 menit yang lalu",
        "Waktu Scrapping": "05 April 2024 17:21:00"
    },
    {
        "Judul": "Estimasi Penumpang Mudik Lebaran Gunakan Kereta Api Capai 7,3 Juta Orang",
        "Kategori": "Ramadhan",
        "Waktu Publish": "51 menit yang lalu",
        "Waktu Scrapping": "05 April 2024 17:21:00"
    },
    {
        "Judul": "Bahaya, Jangan Biasakan Tidur di Kasur yang Sama dengan Bayi",
        "Kategori": "Ameera",
        "Waktu Publish": "52 menit yang lalu",
        "Waktu Scrapping": "05 April 2024 17:21:00"
    },
    {
        "Judul": "Shopee Cup, Turnamen Klub Regional Resmi Pertama di Asia Tenggara",
        "Kategori": "Sport",
        "Waktu Publish": "53 menit yang lalu",
        "Waktu Scrapping": "05 April 2024 17:21:00"
    },
    {
        "Judul": "Jelang Lebaran, Forkopimda Sukabumi Pantau  Harga dan Ketersediaan Sembako",
        "Kategori": "Network",
        "Waktu Publish": "55 menit yang lalu",
        "Waktu Scrapping": "05 April 2024 17:21:00"
    },
    {
        "Judul": "Penampakan Longsor Tol Bocimi",
        "Kategori": "Visual",
        "Waktu Publish": "56 menit yang lalu",
        "Waktu Scrapping": "05 April 2024 17:21:00"
    },
    {
        "Judul": "Usai Jalani Sidang 4,5 Jam, Empat Menteri Jokowi Irit Bicara",
        "Kategori": "News",
        "Waktu Publish": "56 menit yang lalu",
        "Waktu Scrapping": "05 April 2024 17:21:00"
    },
    {
        "Judul": "Astronom Gunakan Teleskop James Webb untuk Berburu Eksoplanet yang Baru Terbentuk",
        "Kategori": "Tekno",
        "Waktu Publish": "1 jam yang lalu",
        "Waktu Scrapping": "05 April 2024 17:21:00"
    },
    {
        "Judul": "Klub Sambut Baik Pengumuman Tanggal Kelanjutan Liga 1",
        "Kategori": "Sport",
        "Waktu Publish": "1 jam yang lalu",
        "Waktu Scrapping": "05 April 2024 17:21:00"
    },
    {
        "Judul": "Pengelola Borobudur Pastikan Kenyamanan dan Keamanan Wisatawan Selama Libur Lebaran",
        "Kategori": "Ramadhan",
        "Waktu Publish": "1 jam yang lalu",
        "Waktu Scrapping": "05 April 2024 17:21:00"
    },
    {
        "Judul": "Kapolres Indramayu Berangkatkan Peserta Mudik Gratis ke Tegal dan Semarang",
        "Kategori": "Rejabar",
        "Waktu Publish": "1 jam yang lalu",
        "Waktu Scrapping": "05 April 2024 17:21:00"
    },
    {
        "Judul": "Airlangga: Perlinsos Mampu Melindungi Masyarakat Miskin di Masa Krisis",
        "Kategori": "Ekonomi",
        "Waktu Publish": "1 jam yang lalu",
        "Waktu Scrapping": "05 April 2024 17:21:00"
    },
    {
        "Judul": "BMKG: Kondisi Cuaca Selama Pekan Mudik Dibagi dalam Tiga Fase Periodik",
        "Kategori": "Tekno",
        "Waktu Publish": "1 jam yang lalu",
        "Waktu Scrapping": "05 April 2024 17:21:00"
    },
    {
        "Judul": "ODGJ Selama Ramadhan: Rajin Tahajud dan Baca Alquran",
        "Kategori": "Ramadhan",
        "Waktu Publish": "1 jam yang lalu",
        "Waktu Scrapping": "05 April 2024 17:21:00"
    },
    {
        "Judul": "Kecelakaan Arus Mudik, Minibus Tabrak Mobil Elf di Tol Cipali Hingga Terguling",
        "Kategori": "News",
        "Waktu Publish": "1 jam yang lalu",
        "Waktu Scrapping": "05 April 2024 17:21:00"
    },
    {
        "Judul": "Sheila On 7 Bakal Sambangi Lima Kota untuk Konser 'Tunggu Aku di...'",
        "Kategori": "Ameera",
        "Waktu Publish": "1 jam yang lalu",
        "Waktu Scrapping": "05 April 2024 17:21:00"
    },
    {
        "Judul": "Jelang Musim Mudik, Dokter Minta Waspadai Infeksi Saluran Kemih",
        "Kategori": "Ameera",
        "Waktu Publish": "1 jam yang lalu",
        "Waktu Scrapping": "05 April 2024 17:21:00"
    },
    {
        "Judul": "H-5, Arus Lalu Lintas di Gerbang Tol Cileunyi Ramai Lancar Hanya Tersendat di Rancaekek",
        "Kategori": "Rejabar",
        "Waktu Publish": "1 jam yang lalu",
        "Waktu Scrapping": "05 April 2024 17:21:00"
    },
    {
        "Judul": "Mudik Bersama United Tractors",
        "Kategori": "Visual",
        "Waktu Publish": "1 jam yang lalu",
        "Waktu Scrapping": "05 April 2024 17:21:00"
    }
]